gitlab_helper/__init__.py
gitlab_helper/cli.py
gitlab_helper/exceptions.py
gitlab_helper/main.py
gitlab_helper/settings/__init__.py
gitlab_helper/settings/base.py
gitlab_helper-0.2.16.dist-info/AUTHORS.rst
gitlab_helper-0.2.16.dist-info/LICENSE
gitlab_helper-0.2.16.dist-info/METADATA
gitlab_helper-0.2.16.dist-info/WHEEL
gitlab_helper-0.2.16.dist-info/entry_points.txt
gitlab_helper-0.2.16.dist-info/top_level.txt
gitlab_helper-0.2.16.dist-info/RECORD
