Metadata-Version: 2.1
Name: gitlab-helper
Version: 0.2.16
Summary: some useful actions for interacting with gitlab
Home-page: https://github.com/reedrichards/glb
Author: Robert Wendt
Author-email: rwendt1337@gmail.com
License: MIT license
Keywords: gitlab_helper
Platform: UNKNOWN
Classifier: Development Status :: 2 - Pre-Alpha
Classifier: Intended Audience :: Developers
Classifier: License :: OSI Approved :: MIT License
Classifier: Natural Language :: English
Classifier: Programming Language :: Python :: 3.7
Requires-Dist: Click (>=6.0)
Requires-Dist: gitpython
Requires-Dist: python-gitlab
Requires-Dist: cookiecutter
